<annotation>
	<folder>data</folder>
	<filename>20200122202001_2df7735ef4de2701000d67b726842d9b_3.jpeg</filename>
	<path>/Users/liubeiming/Desktop/mask-dataset/part1/data/20200122202001_2df7735ef4de2701000d67b726842d9b_3.jpeg</path>
	<source>
		<database>Unknown</database>
	</source>
	<size>
		<width>440</width>
		<height>440</height>
		<depth>3</depth>
	</size>
	<segmented>0</segmented>
	<object>
		<name>wrongmask</name>
		<pose>Unspecified</pose>
		<truncated>0</truncated>
		<difficult>0</difficult>
		<bndbox>
			<xmin>41</xmin>
			<ymin>51</ymin>
			<xmax>176</xmax>
			<ymax>239</ymax>
		</bndbox>
	</object>
	<object>
		<name>wrongmask</name>
		<pose>Unspecified</pose>
		<truncated>0</truncated>
		<difficult>0</difficult>
		<bndbox>
			<xmin>262</xmin>
			<ymin>19</ymin>
			<xmax>417</xmax>
			<ymax>264</ymax>
		</bndbox>
	</object>
	<object>
		<name>wrongmask</name>
		<pose>Unspecified</pose>
		<truncated>0</truncated>
		<difficult>0</difficult>
		<bndbox>
			<xmin>28</xmin>
			<ymin>307</ymin>
			<xmax>114</xmax>
			<ymax>432</ymax>
		</bndbox>
	</object>
	<object>
		<name>wrongmask</name>
		<pose>Unspecified</pose>
		<truncated>0</truncated>
		<difficult>0</difficult>
		<bndbox>
			<xmin>180</xmin>
			<ymin>302</ymin>
			<xmax>265</xmax>
			<ymax>431</ymax>
		</bndbox>
	</object>
	<object>
		<name>wrongmask</name>
		<pose>Unspecified</pose>
		<truncated>0</truncated>
		<difficult>0</difficult>
		<bndbox>
			<xmin>331</xmin>
			<ymin>318</ymin>
			<xmax>403</xmax>
			<ymax>423</ymax>
		</bndbox>
	</object>
</annotation>
